Metadata-Version: 2.1
Name: cazomevolve
Version: 0.1.7.3
Summary: A bioinforamtic package for investigating the evolution of CAZomes
Author: Emma E. M. Hobbs
Author-email: eemh1@st-andrews.ac.uk
License: MIT
Keywords: bioinforamtics protein
Platform: Posix
Platform: MacOS X
Classifier: Development Status :: 3 - Alpha
Classifier: Environment :: Console
Classifier: Intended Audience :: Science/Research
Classifier: License :: OSI Approved :: MIT License
Classifier: Natural Language :: English
Classifier: Operating System :: POSIX :: Linux
Classifier: Operating System :: MacOS :: MacOS X
Classifier: Programming Language :: Python :: 3.8
Classifier: Topic :: Scientific/Engineering :: Bio-Informatics
License-File: LICENSE
Requires-Dist: adjustText
Requires-Dist: bs4
Requires-Dist: biopython
Requires-Dist: cazy-webscraper
Requires-Dist: matplotlib
Requires-Dist: ncbi-genome-download
Requires-Dist: numpy
Requires-Dist: pandas
Requires-Dist: saintbioutils
Requires-Dist: scikit-learn
Requires-Dist: scipy
Requires-Dist: seaborn
Requires-Dist: sqlalchemy
Requires-Dist: tqdm
Requires-Dist: upsetplot
